atomicds/__init__.py
atomscale/__init__.py
atomscale/client.py
atomscale/core/__init__.py
atomscale/core/client.py
atomscale/core/files.py
atomscale/core/utils.py
atomscale/results/__init__.py
atomscale/results/group.py
atomscale/results/metrology.py
atomscale/results/optical.py
atomscale/results/photoluminescence.py
atomscale/results/raman.py
atomscale/results/rheed_image.py
atomscale/results/rheed_video.py
atomscale/results/unknown.py
atomscale/results/xps.py
atomscale/streaming/Cargo.lock
atomscale/streaming/Cargo.toml
atomscale/streaming/__init__.py
atomscale/streaming/rheed_stream.cpython-311-x86_64-linux-gnu.so
atomscale/streaming/rheed_stream.pyi
atomscale/streaming/src/initialize.rs
atomscale/streaming/src/lib.rs
atomscale/streaming/src/upload.rs
atomscale/streaming/src/utils.rs
atomscale/timeseries/__init__.py
atomscale/timeseries/align.py
atomscale/timeseries/metrology.py
atomscale/timeseries/optical.py
atomscale/timeseries/polling.py
atomscale/timeseries/provider.py
atomscale/timeseries/registry.py
atomscale/timeseries/rheed.py
atomscale/timeseries/sample.py
atomscale.libs/libcom_err-2abe824b.so.2.1
atomscale.libs/libcrypto-d3570994.so.1.0.2k
atomscale.libs/libgssapi_krb5-497db0c6.so.2.2
atomscale.libs/libk5crypto-b1f99d5c.so.3.1
atomscale.libs/libkeyutils-dfe70bd6.so.1.5
atomscale.libs/libkrb5-fcafa220.so.3.3
atomscale.libs/libkrb5support-d0bcff84.so.0.1
atomscale.libs/libpcre-9513aab5.so.1.2.0
atomscale.libs/libselinux-0922c95c.so.1
atomscale.libs/libssl-cd1d6220.so.1.0.2k
atomscale-0.7.2.dist-info/METADATA
atomscale-0.7.2.dist-info/WHEEL
atomscale-0.7.2.dist-info/top_level.txt
atomscale-0.7.2.dist-info/RECORD
atomscale-0.7.2.dist-info/licenses/LICENSE
