Metadata-Version: 2.4
Name: atomscale
Version: 0.7.2
Summary: Python SDK for Atomscale.
Author-email: Atomscale <info@atomscale.ai>
License: GPL-3.0-only
Project-URL: Homepage, https://www.atomscale.ai
Project-URL: Documentation, https://atomscale-ai.github.io/sdk
Classifier: Intended Audience :: Science/Research
Classifier: Programming Language :: Python :: 3
Classifier: Programming Language :: Python :: 3.10
Classifier: Programming Language :: Python :: 3.11
Classifier: Programming Language :: Python :: 3.12
Classifier: Intended Audience :: Science/Research
Classifier: Topic :: Scientific/Engineering
Classifier: Operating System :: Microsoft :: Windows
Classifier: Operating System :: Unix
Classifier: Operating System :: MacOS
Requires-Python: <3.13,>=3.10
License-File: LICENSE
Requires-Dist: numpy
Requires-Dist: pandas
Requires-Dist: monty
Requires-Dist: pillow
Requires-Dist: networkx
Requires-Dist: requests
Requires-Dist: rich
Requires-Dist: matplotlib
Requires-Dist: pycocotools
Requires-Dist: trackpy
Provides-Extra: dev
Requires-Dist: pytest; extra == "dev"
Requires-Dist: pytest-httpserver; extra == "dev"
Requires-Dist: pytest-cov; extra == "dev"
Requires-Dist: pytest-order; extra == "dev"
Requires-Dist: pytest-dependency; extra == "dev"
Requires-Dist: pytest-asyncio; extra == "dev"
Requires-Dist: ruff; extra == "dev"
Requires-Dist: mypy; extra == "dev"
Requires-Dist: types-requests; extra == "dev"
Requires-Dist: pandas-stubs; extra == "dev"
Provides-Extra: docs
Requires-Dist: sphinx>=6.2; extra == "docs"
Requires-Dist: sphinx-autodoc-typehints>=1.24; extra == "docs"
Requires-Dist: alabaster>=0.7; extra == "docs"
Dynamic: license-file
